ncache/__init__.py
ncache/client/Cache.py
ncache/client/CacheConnection.py
ncache/client/CacheConnectionOptions.py
ncache/client/CacheEventArg.py
ncache/client/CacheEventDescriptor.py
ncache/client/CacheItem.py
ncache/client/CacheItemVersion.py
ncache/client/CacheManager.py
ncache/client/ClientInfo.py
ncache/client/ClusterEvent.py
ncache/client/LockHandle.py
ncache/client/ServerInfo.py
ncache/client/__init__.py
ncache/client/enum/CacheItemPriority.py
ncache/client/enum/CacheItemRemovedReason.py
ncache/client/enum/CacheStatusNotificationType.py
ncache/client/enum/ClientCacheSyncMode.py
ncache/client/enum/CmdParamsType.py
ncache/client/enum/CommandType.py
ncache/client/enum/ConnectivityStatus.py
ncache/client/enum/DataTypeEventDataFilter.py
ncache/client/enum/DeliveryMode.py
ncache/client/enum/DeliveryOption.py
ncache/client/enum/DistributedDataStructure.py
ncache/client/enum/EntryType.py
ncache/client/enum/EventDataFilter.py
ncache/client/enum/EventType.py
ncache/client/enum/ExpirationType.py
ncache/client/enum/IsolationLevel.py
ncache/client/enum/LogLevel.py
ncache/client/enum/MessgeFailureReason.py
ncache/client/enum/OpType.py
ncache/client/enum/ReadMode.py
ncache/client/enum/SubscriptionPolicy.py
ncache/client/enum/TopicPriority.py
ncache/client/enum/TopicSearchOptions.py
ncache/client/enum/WriteMode.py
ncache/client/enum/__init__.py
ncache/client/services/MessagingService.py
ncache/client/services/__init__.py
ncache/lib/__init__.py
ncache/lib/cache-api-1.1.1.jar
ncache/lib/db2jcc_license_cu.jar
ncache/lib/guava-13.0.1.jar
ncache/lib/guava-28.1-jre.jar
ncache/lib/guava-gwt-28.1-jre.jar
ncache/lib/guice-3.0.jar
ncache/lib/guice-multibindings-3.0.jar
ncache/lib/jackson-annotations-2.10.1.jar
ncache/lib/jackson-core-2.10.1.jar
ncache/lib/jackson-databind-2.10.1.jar
ncache/lib/jakarta.nc-sessionprovider.jar
ncache/lib/jakarta.servlet-api-1.1.0.6-jre15.jar
ncache/lib/javassist.jar
ncache/lib/javax.nc-sessionprovider.jar
ncache/lib/javax.servlet-api-4.0.0.jar
ncache_professional_client-5.3.0.dist-info/LICENSE
ncache_professional_client-5.3.0.dist-info/METADATA
ncache_professional_client-5.3.0.dist-info/WHEEL
ncache_professional_client-5.3.0.dist-info/top_level.txt
ncache_professional_client-5.3.0.dist-info/RECORD
