Metadata-Version: 2.1
Name: ncache-professional-client
Version: 5.3.0
Summary: NCache Professional Python Client Package.
Author: Alachisoft
License: UNKNOWN
Platform: UNKNOWN
Classifier: Programming Language :: Python :: 3
Classifier: License :: OSI Approved :: MIT License
Classifier: Operating System :: OS Independent
Requires-Python: >=3.5
License-File: LICENSE
Requires-Dist: jpype1
Requires-Dist: jsons
